accountutils/__init__.py
accountutils/admin.py
accountutils/app_settings.py
accountutils/apps.py
accountutils/fields.py
accountutils/models.py
accountutils/tests.py
accountutils/urls.py
accountutils/utils.py
accountutils/views.py
accountutils/migrations/0001_initial.py
accountutils/migrations/__init__.py
django_accountutils-0.7.dist-info/METADATA
django_accountutils-0.7.dist-info/RECORD
django_accountutils-0.7.dist-info/WHEEL
django_accountutils-0.7.dist-info/top_level.txt
